{
  "width": 32,
  "height": 32,
  "background": "#00000000",
  "pixels": [
    {"x":14,"y":1,"color":"#000000"},{"x":15,"y":1,"color":"#000000"},{"x":16,"y":1,"color":"#000000"},
    {"x":13,"y":2,"color":"#000000"},{"x":14,"y":2,"color":"#ffb691"},{"x":15,"y":2,"color":"#ffd3af"},{"x":16,"y":2,"color":"#ca8f72"},{"x":17,"y":2,"color":"#000000"},
    {"x":12,"y":3,"color":"#000000"},{"x":13,"y":3,"color":"#ffd3af"},{"x":14,"y":3,"color":"#ffb691"},{"x":15,"y":3,"color":"#ffb691"},{"x":16,"y":3,"color":"#ca8f72"},{"x":17,"y":3,"color":"#a5765e"},{"x":18,"y":3,"color":"#000000"},
    {"x":12,"y":4,"color":"#000000"},{"x":13,"y":4,"color":"#ffb691"},{"x":14,"y":4,"color":"#ca8f72"},{"x":15,"y":4,"color":"#ca8f72"},{"x":16,"y":4,"color":"#ca8f72"},{"x":17,"y":4,"color":"#7f5a48"},{"x":18,"y":4,"color":"#000000"},
    {"x":11,"y":5,"color":"#000000"},{"x":12,"y":5,"color":"#1a3a6e"},{"x":13,"y":5,"color":"#2a5299"},{"x":14,"y":5,"color":"#ffb691"},{"x":15,"y":5,"color":"#ca8f72"},{"x":16,"y":5,"color":"#a5765e"},{"x":17,"y":5,"color":"#2a5299"},{"x":18,"y":5,"color":"#1a3a6e"},{"x":19,"y":5,"color":"#000000"},
    {"x":10,"y":6,"color":"#000000"},{"x":11,"y":6,"color":"#1a3a6e"},{"x":12,"y":6,"color":"#4a7ac7"},{"x":13,"y":6,"color":"#7ab3f7"},{"x":14,"y":6,"color":"#ffb691"},{"x":15,"y":6,"color":"#ffb691"},{"x":16,"y":6,"color":"#7ab3f7"},{"x":17,"y":6,"color":"#4a7ac7"},{"x":18,"y":6,"color":"#1a3a6e"},{"x":19,"y":6,"color":"#000000"},
    {"x":9,"y":7,"color":"#000000"},{"x":10,"y":7,"color":"#1a3a6e"},{"x":11,"y":7,"color":"#4a7ac7"},{"x":12,"y":7,"color":"#7ab3f7"},{"x":13,"y":7,"color":"#a8d4ff"},{"x":14,"y":7,"color":"#7ab3f7"},{"x":15,"y":7,"color":"#a8d4ff"},{"x":16,"y":7,"color":"#7ab3f7"},{"x":17,"y":7,"color":"#4a7ac7"},{"x":18,"y":7,"color":"#1a3a6e"},{"x":19,"y":7,"color":"#0a2a5e"},{"x":20,"y":7,"color":"#000000"},
    {"x":8,"y":8,"color":"#000000"},{"x":9,"y":8,"color":"#0a2a5e"},{"x":10,"y":8,"color":"#2a5299"},{"x":11,"y":8,"color":"#7ab3f7"},{"x":12,"y":8,"color":"#a8d4ff"},{"x":13,"y":8,"color":"#7ab3f7"},{"x":14,"y":8,"color":"#ffd700"},{"x":15,"y":8,"color":"#ffd700"},{"x":16,"y":8,"color":"#7ab3f7"},{"x":17,"y":8,"color":"#a8d4ff"},{"x":18,"y":8,"color":"#4a7ac7"},{"x":19,"y":8,"color":"#1a3a6e"},{"x":20,"y":8,"color":"#0a2a5e"},{"x":21,"y":8,"color":"#000000"},
    {"x":7,"y":9,"color":"#000000"},{"x":8,"y":9,"color":"#0a2a5e"},{"x":9,"y":9,"color":"#1a3a6e"},{"x":10,"y":9,"color":"#4a7ac7"},{"x":11,"y":9,"color":"#7ab3f7"},{"x":12,"y":9,"color":"#ffd700"},{"x":13,"y":9,"color":"#ffec80"},{"x":14,"y":9,"color":"#ffd700"},{"x":15,"y":9,"color":"#ca8f00"},{"x":16,"y":9,"color":"#ffd700"},{"x":17,"y":9,"color":"#7ab3f7"},{"x":18,"y":9,"color":"#4a7ac7"},{"x":19,"y":9,"color":"#1a3a6e"},{"x":20,"y":9,"color":"#0a2a5e"},{"x":21,"y":9,"color":"#0a1a3e"},{"x":22,"y":9,"color":"#000000"},
    {"x":6,"y":10,"color":"#000000"},{"x":7,"y":10,"color":"#0a2a5e"},{"x":8,"y":10,"color":"#2a5299"},{"x":9,"y":10,"color":"#7ab3f7"},{"x":10,"y":10,"color":"#a8d4ff"},{"x":11,"y":10,"color":"#7ab3f7"},{"x":12,"y":10,"color":"#ffd700"},{"x":13,"y":10,"color":"#ffec80"},{"x":14,"y":10,"color":"#ca8f00"},{"x":15,"y":10,"color":"#9a6f00"},{"x":16,"y":10,"color":"#ffd700"},{"x":17,"y":10,"color":"#a8d4ff"},{"x":18,"y":10,"color":"#4a7ac7"},{"x":19,"y":10,"color":"#1a3a6e"},{"x":20,"y":10,"color":"#0a2a5e"},{"x":21,"y":10,"color":"#000000"},
    {"x":5,"y":11,"color":"#000000"},{"x":6,"y":11,"color":"#0a2a5e"},{"x":7,"y":11,"color":"#1a3a6e"},{"x":8,"y":11,"color":"#4a7ac7"},{"x":9,"y":11,"color":"#7ab3f7"},{"x":10,"y":11,"color":"#a8d4ff"},{"x":11,"y":11,"color":"#7ab3f7"},{"x":12,"y":11,"color":"#a8d4ff"},{"x":13,"y":11,"color":"#7ab3f7"},{"x":14,"y":11,"color":"#4a7ac7"},{"x":15,"y":11,"color":"#7ab3f7"},{"x":16,"y":11,"color":"#a8d4ff"},{"x":17,"y":11,"color":"#4a7ac7"},{"x":18,"y":11,"color":"#1a3a6e"},{"x":19,"y":11,"color":"#0a2a5e"},{"x":20,"y":11,"color":"#000000"},
    {"x":4,"y":12,"color":"#000000"},{"x":5,"y":12,"color":"#0a2a5e"},{"x":6,"y":12,"color":"#2a5299"},{"x":7,"y":12,"color":"#4a7ac7"},{"x":8,"y":12,"color":"#7ab3f7"},{"x":9,"y":12,"color":"#a8d4ff"},{"x":10,"y":12,"color":"#7ab3f7"},{"x":11,"y":12,"color":"#4a7ac7"},{"x":12,"y":12,"color":"#2a5299"},{"x":13,"y":12,"color":"#4a7ac7"},{"x":14,"y":12,"color":"#7ab3f7"},{"x":15,"y":12,"color":"#4a7ac7"},{"x":16,"y":12,"color":"#7ab3f7"},{"x":17,"y":12,"color":"#2a5299"},{"x":18,"y":12,"color":"#1a3a6e"},{"x":19,"y":12,"color":"#0a2a5e"},{"x":20,"y":12,"color":"#0a1a3e"},{"x":21,"y":12,"color":"#000000"},
    {"x":3,"y":13,"color":"#000000"},{"x":4,"y":13,"color":"#0a1a3e"},{"x":5,"y":13,"color":"#1a3a6e"},{"x":6,"y":13,"color":"#4a7ac7"},{"x":7,"y":13,"color":"#7ab3f7"},{"x":8,"y":13,"color":"#a8d4ff"},{"x":9,"y":13,"color":"#7ab3f7"},{"x":10,"y":13,"color":"#4a7ac7"},{"x":11,"y":13,"color":"#000000"},{"x":12,"y":13,"color":"#000000"},{"x":13,"y":13,"color":"#4a7ac7"},{"x":14,"y":13,"color":"#7ab3f7"},{"x":15,"y":13,"color":"#4a7ac7"},{"x":16,"y":13,"color":"#7ab3f7"},{"x":17,"y":13,"color":"#2a5299"},{"x":18,"y":13,"color":"#1a3a6e"},{"x":19,"y":13,"color":"#0a2a5e"},{"x":20,"y":13,"color":"#000000"},
    {"x":2,"y":14,"color":"#000000"},{"x":3,"y":14,"color":"#0a1a3e"},{"x":4,"y":14,"color":"#1a3a6e"},{"x":5,"y":14,"color":"#4a7ac7"},{"x":6,"y":14,"color":"#7ab3f7"},{"x":7,"y":14,"color":"#a8d4ff"},{"x":8,"y":14,"color":"#7ab3f7"},{"x":9,"y":14,"color":"#4a7ac7"},{"x":10,"y":14,"color":"#000000"},{"x":15,"y":14,"color":"#000000"},{"x":16,"y":14,"color":"#4a7ac7"},{"x":17,"y":14,"color":"#7ab3f7"},{"x":18,"y":14,"color":"#1a3a6e"},{"x":19,"y":14,"color":"#0a2a5e"},{"x":20,"y":14,"color":"#000000"},
    {"x":1,"y":15,"color":"#000000"},{"x":2,"y":15,"color":"#0a1a3e"},{"x":3,"y":15,"color":"#2a5299"},{"x":4,"y":15,"color":"#4a7ac7"},{"x":5,"y":15,"color":"#7ab3f7"},{"x":6,"y":15,"color":"#a8d4ff"},{"x":7,"y":15,"color":"#7ab3f7"},{"x":8,"y":15,"color":"#4a7ac7"},{"x":9,"y":15,"color":"#1a3a6e"},{"x":10,"y":15,"color":"#000000"},{"x":15,"y":15,"color":"#000000"},{"x":16,"y":15,"color":"#1a3a6e"},{"x":17,"y":15,"color":"#4a7ac7"},{"x":18,"y":15,"color":"#2a5299"},{"x":19,"y":15,"color":"#0a2a5e"},{"x":20,"y":15,"color":"#000000"},
    {"x":1,"y":16,"color":"#000000"},{"x":2,"y":16,"color":"#1a3a6e"},{"x":3,"y":16,"color":"#4a7ac7"},{"x":4,"y":16,"color":"#7ab3f7"},{"x":5,"y":16,"color":"#a8d4ff"},{"x":6,"y":16,"color":"#7ab3f7"},{"x":7,"y":16,"color":"#4a7ac7"},{"x":8,"y":16,"color":"#1a3a6e"},{"x":9,"y":16,"color":"#000000"},{"x":10,"y":16,"color":"#000000"},{"x":15,"y":16,"color":"#000000"},{"x":16,"y":16,"color":"#000000"},{"x":17,"y":16,"color":"#1a3a6e"},{"x":18,"y":16,"color":"#4a7ac7"},{"x":19,"y":16,"color":"#1a3a6e"},{"x":20,"y":16,"color":"#000000"},
    {"x":2,"y":17,"color":"#000000"},{"x":3,"y":17,"color":"#0a2a5e"},{"x":4,"y":17,"color":"#2a5299"},{"x":5,"y":17,"color":"#4a7ac7"},{"x":6,"y":17,"color":"#7ab3f7"},{"x":7,"y":17,"color":"#4a7ac7"},{"x":8,"y":17,"color":"#1a3a6e"},{"x":9,"y":17,"color":"#0a2a5e"},{"x":10,"y":17,"color":"#000000"},{"x":17,"y":17,"color":"#000000"},{"x":18,"y":17,"color":"#0a2a5e"},{"x":19,"y":17,"color":"#1a3a6e"},{"x":20,"y":17,"color":"#000000"},
    {"x":3,"y":18,"color":"#000000"},{"x":4,"y":18,"color":"#0a1a3e"},{"x":5,"y":18,"color":"#1a3a6e"},{"x":6,"y":18,"color":"#4a7ac7"},{"x":7,"y":18,"color":"#2a5299"},{"x":8,"y":18,"color":"#1a3a6e"},{"x":9,"y":18,"color":"#000000"},{"x":18,"y":18,"color":"#000000"},{"x":19,"y":18,"color":"#1a3a6e"},{"x":20,"y":18,"color":"#000000"},
    {"x":4,"y":19,"color":"#000000"},{"x":5,"y":19,"color":"#0a2a5e"},{"x":6,"y":19,"color":"#2a5299"},{"x":7,"y":19,"color":"#1a3a6e"},{"x":8,"y":19,"color":"#0a2a5e"},{"x":9,"y":19,"color":"#000000"},{"x":10,"y":19,"color":"#000000"},{"x":11,"y":19,"color":"#000000"},{"x":12,"y":19,"color":"#0a2a5e"},{"x":13,"y":19,"color":"#1a3a6e"},{"x":14,"y":19,"color":"#2a5299"},{"x":15,"y":19,"color":"#4a7ac7"},{"x":16,"y":19,"color":"#2a5299"},{"x":17,"y":19,"color":"#0a2a5e"},{"x":18,"y":19,"color":"#000000"},
    {"x":5,"y":20,"color":"#000000"},{"x":6,"y":20,"color":"#000000"},{"x":7,"y":20,"color":"#000000"},{"x":8,"y":20,"color":"#000000"},{"x":9,"y":20,"color":"#000000"},{"x":10,"y":20,"color":"#0a2a5e"},{"x":11,"y":20,"color":"#2a5299"},{"x":12,"y":20,"color":"#4a7ac7"},{"x":13,"y":20,"color":"#7ab3f7"},{"x":14,"y":20,"color":"#a8d4ff"},{"x":15,"y":20,"color":"#7ab3f7"},{"x":16,"y":20,"color":"#4a7ac7"},{"x":17,"y":20,"color":"#1a3a6e"},{"x":18,"y":20,"color":"#000000"},
    {"x":9,"y":21,"color":"#000000"},{"x":10,"y":21,"color":"#0a2a5e"},{"x":11,"y":21,"color":"#2a5299"},{"x":12,"y":21,"color":"#4a7ac7"},{"x":13,"y":21,"color":"#7ab3f7"},{"x":14,"y":21,"color":"#a8d4ff"},{"x":15,"y":21,"color":"#7ab3f7"},{"x":16,"y":21,"color":"#4a7ac7"},{"x":17,"y":21,"color":"#1a3a6e"},{"x":18,"y":21,"color":"#0a2a5e"},{"x":19,"y":21,"color":"#000000"},
    {"x":8,"y":22,"color":"#000000"},{"x":9,"y":22,"color":"#0a2a5e"},{"x":10,"y":22,"color":"#1a3a6e"},{"x":11,"y":22,"color":"#4a7ac7"},{"x":12,"y":22,"color":"#7ab3f7"},{"x":13,"y":22,"color":"#a8d4ff"},{"x":14,"y":22,"color":"#a8d4ff"},{"x":15,"y":22,"color":"#7ab3f7"},{"x":16,"y":22,"color":"#4a7ac7"},{"x":17,"y":22,"color":"#1a3a6e"},{"x":18,"y":22,"color":"#0a2a5e"},{"x":19,"y":22,"color":"#000000"},
    {"x":8,"y":23,"color":"#000000"},{"x":9,"y":23,"color":"#1a3a6e"},{"x":10,"y":23,"color":"#4a7ac7"},{"x":11,"y":23,"color":"#7ab3f7"},{"x":12,"y":23,"color":"#a8d4ff"},{"x":13,"y":23,"color":"#7ab3f7"},{"x":14,"y":23,"color":"#7ab3f7"},{"x":15,"y":23,"color":"#4a7ac7"},{"x":16,"y":23,"color":"#2a5299"},{"x":17,"y":23,"color":"#0a2a5e"},{"x":18,"y":23,"color":"#000000"},
    {"x":7,"y":24,"color":"#000000"},{"x":8,"y":24,"color":"#0a2a5e"},{"x":9,"y":24,"color":"#2a5299"},{"x":10,"y":24,"color":"#4a7ac7"},{"x":11,"y":24,"color":"#7ab3f7"},{"x":12,"y":24,"color":"#4a7ac7"},{"x":13,"y":24,"color":"#4a7ac7"},{"x":14,"y":24,"color":"#2a5299"},{"x":15,"y":24,"color":"#1a3a6e"},{"x":16,"y":24,"color":"#0a2a5e"},{"x":17,"y":24,"color":"#000000"},
    {"x":7,"y":25,"color":"#000000"},{"x":8,"y":25,"color":"#1a3a6e"},{"x":9,"y":25,"color":"#4a7ac7"},{"x":10,"y":25,"color":"#7ab3f7"},{"x":11,"y":25,"color":"#4a7ac7"},{"x":12,"y":25,"color":"#2a5299"},{"x":13,"y":25,"color":"#2a5299"},{"x":14,"y":25,"color":"#1a3a6e"},{"x":15,"y":25,"color":"#0a2a5e"},{"x":16,"y":25,"color":"#000000"},
    {"x":6,"y":26,"color":"#000000"},{"x":7,"y":26,"color":"#0a2a5e"},{"x":8,"y":26,"color":"#2a5299"},{"x":9,"y":26,"color":"#4a7ac7"},{"x":10,"y":26,"color":"#2a5299"},{"x":11,"y":26,"color":"#1a3a6e"},{"x":12,"y":26,"color":"#0a2a5e"},{"x":13,"y":26,"color":"#0a2a5e"},{"x":14,"y":26,"color":"#000000"},{"x":15,"y":26,"color":"#000000"},
    {"x":6,"y":27,"color":"#000000"},{"x":7,"y":27,"color":"#1a3a6e"},{"x":8,"y":27,"color":"#4a7ac7"},{"x":9,"y":27,"color":"#2a5299"},{"x":10,"y":27,"color":"#0a2a5e"},{"x":11,"y":27,"color":"#000000"},{"x":14,"y":27,"color":"#000000"},{"x":15,"y":27,"color":"#0a2a5e"},{"x":16,"y":27,"color":"#2a5299"},{"x":17,"y":27,"color":"#4a7ac7"},{"x":18,"y":27,"color":"#1a3a6e"},{"x":19,"y":27,"color":"#000000"},
    {"x":5,"y":28,"color":"#000000"},{"x":6,"y":28,"color":"#0a2a5e"},{"x":7,"y":28,"color":"#1a3a6e"},{"x":8,"y":28,"color":"#2a5299"},{"x":9,"y":28,"color":"#0a2a5e"},{"x":10,"y":28,"color":"#000000"},{"x":15,"y":28,"color":"#000000"},{"x":16,"y":28,"color":"#0a2a5e"},{"x":17,"y":28,"color":"#2a5299"},{"x":18,"y":28,"color":"#1a3a6e"},{"x":19,"y":28,"color":"#0a2a5e"},{"x":20,"y":28,"color":"#000000"},
    {"x":5,"y":29,"color":"#000000"},{"x":6,"y":29,"color":"#0a2a5e"},{"x":7,"y":29,"color":"#1a3a6e"},{"x":8,"y":29,"color":"#0a2a5e"},{"x":9,"y":29,"color":"#000000"},{"x":16,"y":29,"color":"#000000"},{"x":17,"y":29,"color":"#0a2a5e"},{"x":18,"y":29,"color":"#1a3a6e"},{"x":19,"y":29,"color":"#0a2a5e"},{"x":20,"y":29,"color":"#000000"},
    {"x":5,"y":30,"color":"#000000"},{"x":6,"y":30,"color":"#0a1a3e"},{"x":7,"y":30,"color":"#0a2a5e"},{"x":8,"y":30,"color":"#000000"},{"x":17,"y":30,"color":"#000000"},{"x":18,"y":30,"color":"#0a2a5e"},{"x":19,"y":30,"color":"#0a1a3e"},{"x":20,"y":30,"color":"#000000"},
    {"x":6,"y":31,"color":"#000000"},{"x":7,"y":31,"color":"#000000"},{"x":18,"y":31,"color":"#000000"},{"x":19,"y":31,"color":"#000000"}
  ]
}
